{
    "prepare_queue": {
        "installed": [],
        "uninstalled": []
    },
    "config_munge": {
        "files": {}
    },
    "installed_plugins": {
        "cordova-plugin-console": {
            "PACKAGE_NAME": "com.umts.pvtamultiplaform"
        },
        "cordova-plugin-device": {
            "PACKAGE_NAME": "com.umts.pvtamultiplaform"
        },
        "cordova-plugin-geolocation": {
            "PACKAGE_NAME": "com.umts.pvtamultiplaform"
        },
        "cordova-plugin-inappbrowser": {
            "PACKAGE_NAME": "com.umts.pvtamultiplaform"
        },
        "cordova-plugin-splashscreen": {
            "PACKAGE_NAME": "com.umts.pvtamultiplaform"
        },
        "cordova-plugin-statusbar": {
            "PACKAGE_NAME": "com.umts.pvtamultiplaform"
        },
        "cordova-plugin-whitelist": {
            "PACKAGE_NAME": "com.umts.pvtamultiplaform"
        },
        "cordova-plugin-x-toast": {
            "PACKAGE_NAME": "com.umts.pvtamultiplaform"
        },
        "ionic-plugin-keyboard": {
            "PACKAGE_NAME": "com.umts.pvtamultiplaform"
        }
    },
    "dependent_plugins": {
        "cordova-plugin-compat": {
            "PACKAGE_NAME": "com.umts.pvtamultiplaform"
        }
    }
}